mf2/__init__.py
mf2/bohachevsky.py
mf2/booth.py
mf2/borehole.py
mf2/branin.py
mf2/currin.py
mf2/forrester.py
mf2/hartmann.py
mf2/himmelblau.py
mf2/multi_fidelity_function.py
mf2/park91a.py
mf2/park91b.py
mf2/six_hump_camelback.py
mf2/adjustable/__init__.py
mf2/adjustable/branin.py
mf2/adjustable/hartmann.py
mf2/adjustable/paciorek.py
mf2/adjustable/trid.py
tests/__init__.py
tests/multi_fidelity_function_test.py
tests/property_test.py
tests/regression_test.py
tests/utils.py
mf2-2022.6.0.dist-info/LICENSE
mf2-2022.6.0.dist-info/METADATA
mf2-2022.6.0.dist-info/WHEEL
mf2-2022.6.0.dist-info/top_level.txt
mf2-2022.6.0.dist-info/RECORD
