Metadata-Version: 2.1
Name: mf2
Version: 2022.6.0
Summary: A collection of analytical benchmark functions in multiple fidelities
Home-page: https://github.com/sjvrijn/mf2
Author: Sander van Rijn
Author-email: s.j.van.rijn@liacs.leidenuniv.nl
Classifier: Programming Language :: Python :: 3.6
Classifier: Programming Language :: Python :: 3.7
Classifier: Programming Language :: Python :: 3.8
Classifier: Programming Language :: Python :: 3.9
Classifier: Programming Language :: Python :: 3.10
Classifier: Intended Audience :: Science/Research
Classifier: License :: OSI Approved :: GNU General Public License v3 (GPLv3)
Requires-Python: >=3.6
License-File: LICENSE
Requires-Dist: numpy
Provides-Extra: dev
Requires-Dist: hypothesis[numpy] ; extra == 'dev'
Requires-Dist: matplotlib ; extra == 'dev'
Requires-Dist: pandas ; extra == 'dev'
Requires-Dist: pyprojroot ; extra == 'dev'
Requires-Dist: pytest ; extra == 'dev'
Requires-Dist: pytest-cov ; extra == 'dev'
Requires-Dist: pytest-regressions ; extra == 'dev'
Requires-Dist: sphinx ; extra == 'dev'
Requires-Dist: sphinx-rtd-theme ; extra == 'dev'
